djangondor/__about__.py
djangondor/__init__.py
djangondor/collections.py
djangondor/requests.py
djangondor/time.py
djangondor/templatetags/__init__.py
djangondor/templatetags/djangondor_collection_tags.py
djangondor/templatetags/djangondor_path_tags.py
djangondor-0.0.4.dist-info/METADATA
djangondor-0.0.4.dist-info/WHEEL
djangondor-0.0.4.dist-info/licenses/LICENSE.txt
djangondor-0.0.4.dist-info/RECORD
